setup.py
monque/__init__.py
monque/config.py
monque/instance.py
monque/queue.py
monque/task.py
monque/worker.py
monque/worker_main.py
monque.egg-info/PKG-INFO
monque.egg-info/SOURCES.txt
monque.egg-info/dependency_links.txt
monque.egg-info/not-zip-safe
monque.egg-info/top_level.txt