Metadata-Version: 1.0
Name: monque
Version: 0.2.3
Summary: Persistent task queue built on top of MongoDB
Home-page: http://github.com/jslade/python-monque
Author: Jeremy Slade
Author-email: jeremy@jkslade.net
License: MIT
Platform: UNKNOWN
